FOXREG/__init__.py
FOXREG/core.py
FOXREG/diagnostics.py
foxreg-0.1.2.dist-info/METADATA
foxreg-0.1.2.dist-info/WHEEL
foxreg-0.1.2.dist-info/top_level.txt
foxreg-0.1.2.dist-info/RECORD
