Metadata-Version: 2.4
Name: FOXREG
Version: 0.1.2
Summary: A toolkit for regulatory comparison using AUCell and RSS
Home-page: https://github.com/Howard-Fox-Lab/FOX-Functional-OMIC-eXploration
Author: Moses Apostol
Author-email: mapostol@unmc.edu
Classifier: Programming Language :: Python :: 3
Classifier: License :: OSI Approved :: MIT License
Requires-Python: >=3.7
Requires-Dist: numpy
Requires-Dist: pandas
Requires-Dist: scipy
Requires-Dist: scikit-learn
Requires-Dist: matplotlib
Requires-Dist: seaborn
Dynamic: author
Dynamic: author-email
Dynamic: classifier
Dynamic: description
Dynamic: description-content-type
Dynamic: home-page
Dynamic: requires-dist
Dynamic: requires-python
Dynamic: summary
